mobile_automation_library/AppKeyword.py
mobile_automation_library/__init__.py
mobile_automation_library-0.1.dist-info/LICENSE
mobile_automation_library-0.1.dist-info/METADATA
mobile_automation_library-0.1.dist-info/WHEEL
mobile_automation_library-0.1.dist-info/top_level.txt
mobile_automation_library-0.1.dist-info/RECORD
