Metadata-Version: 2.1
Name: mobile_automation_library
Version: 0.1
Summary: Uma biblioteca para automação mobile com Robot Framework
Home-page: https://github.com/Skisperd/libray_robotframework
Author: Tiago Dias
Author-email: tiagooliveira.qa@gmail.com
Classifier: Programming Language :: Python :: 3
Classifier: License :: OSI Approved :: MIT License
Classifier: Operating System :: OS Independent
Classifier: Framework :: Robot Framework
Requires-Python: >=3.6
License-File: LICENSE
Requires-Dist: robotframework
Requires-Dist: Appium-Python-Client
Requires-Dist: robotframework-appiumlibrary
